cpf_field/__init__.py
cpf_field/forms.py
cpf_field/models.py
cpf_field/validators.py
tests/__init__.py
tests/settings.py
tests/tests.py
django_cpf-0.1.0.dist-info/LICENSE
django_cpf-0.1.0.dist-info/METADATA
django_cpf-0.1.0.dist-info/WHEEL
django_cpf-0.1.0.dist-info/top_level.txt
django_cpf-0.1.0.dist-info/RECORD
