Metadata-Version: 2.1
Name: django-cpf
Version: 0.1.0
Summary: Campo CPF Field para usar no Model e ModelForm
Home-page: https://github.com/gabrielloliveira/django-cpf
Author: Gabriell Oliveira
Author-email: gabrielloliveira097@gmail.com
License: MIT
Platform: UNKNOWN
Classifier: Environment :: Web Environment
Classifier: Framework :: Django :: 3.0
Classifier: Intended Audience :: Developers
Classifier: License :: OSI Approved :: MIT License
Classifier: Operating System :: OS Independent
Classifier: Programming Language :: Python :: 3
Requires-Python: >=3.6
